{"5554926755": {"available": "apr 12", "content": 2347, "laundry": "w/d in unit", "furnished": NaN, "price": 1307, "time": "15:21:12", "dog": 1, "bed": 0, "bath": 1, "feet": 594, "date": "2016-04-24", "long": -122.656581, "parking": "detached garage", "lat": 45.530813, "smoking": "no smoking", "getphotos": 19, "cat": 1, "hasmap": 1, "wheelchair": "wheelchair accessible", "housingtype": "apartment"}, "5519250345": {"available": "apr 01", "content": 1981, "laundry": "laundry on site", "furnished": NaN, "price": 150, "time": "18:06:11", "dog": 0, "bed": 0, "bath": NaN, "feet": NaN, "date": "2016-04-01", "long": -119.064, "parking": "off-street parking", "lat": 47.3014, "smoking": NaN, "getphotos": 0, "cat": 0, "hasmap": 1, "wheelchair": NaN, "housingtype": "land"}, "5536154415": {"available": "may 01", "content": 1927, "laundry": "w/d in unit", "furnished": NaN, "price": 1050, "time": "13:42:18", "dog": 1, "bed": 2, "bath": 1, "feet": 870, "date": "2016-04-12", "long": -122.416213, "parking": "off-street parking", "lat": 45.497293, "smoking": "no smoking", "getphotos": 16, "cat": 1, "hasmap": 1, "wheelchair": NaN, "housingtype": "apartment"}, "5562440255": {"available": "may 01", "feet": 1066, "laundry": "w/d in unit", "furnished": NaN, "price": 2360, "parking": "attached garage", "dog": 1, "bed": 3, "bath": 2, "content": 1676, "lat": 45.511558, "long": -122.680334, "time": "10:03:17", "date": "2016-04-29", "smoking": "no smoking", "getphotos": 13, "cat": 1, "hasmap": 1, "wheelchair": "wheelchair accessible", "housingtype": "apartment"}, "5562449525": {"available": "may 05", "feet": 580, "laundry": "w/d in unit", "furnished": NaN, "price": 1529, "parking": "attached garage", "dog": 1, "bed": 1, "bath": 1, "content": 3159, "lat": 45.533256, "long": -122.683523, "time": "10:08:09", "date": "2016-04-29", "smoking": "no smoking", "getphotos": 20, "cat": 1, "hasmap": 1, "wheelchair": "wheelchair accessible", "housingtype": "apartment"}, "5562431974": {"available": "apr 29", "feet": 611, "laundry": "laundry in bldg", "furnished": NaN, "price": 1754, "parking": "detached garage", "dog": 1, "bed": 1, "bath": 1, "content": 3092, "lat": 45.510242, "long": -122.679198, "time": "09:58:54", "date": "2016-04-29", "smoking": "no smoking", "getphotos": 6, "cat": 1, "hasmap": 1, "wheelchair": NaN, "housingtype": "apartment"}, "5550000343": {"available": "apr 21", "content": 2730, "laundry": "w/d in unit", "furnished": NaN, "price": 2366, "time": "11:07:27", "dog": 1, "bed": 1, "bath": 1, "feet": 1027, "date": "2016-04-21", "long": -122.656578, "parking": "detached garage", "lat": 45.530473, "smoking": "no smoking", "getphotos": 10, "cat": 1, "hasmap": 1, "wheelchair": "wheelchair accessible", "housingtype": "apartment"}, "5562422090": {"available": "apr 29", "content": 1240, "laundry": "laundry on site", "furnished": NaN, "price": 1450, "time": "09:53:36", "dog": 1, "bed": 1, "bath": 1, "feet": 625, "date": "2016-04-29", "long": -122.675541, "parking": NaN, "lat": 45.550563, "smoking": NaN, "getphotos": 5, "cat": 1, "hasmap": 1, "wheelchair": NaN, "housingtype": "apartment"}, "5562420518": {"available": "apr 29", "content": 628, "laundry": NaN, "furnished": NaN, "price": 900, "time": "09:52:45", "dog": 0, "bed": 3, "bath": 1, "feet": NaN, "date": "2016-04-29", "long": -122.6832, "parking": NaN, "lat": 45.2514, "smoking": NaN, "getphotos": 0, "cat": 0, "hasmap": 1, "wheelchair": NaN, "housingtype": "apartment"}, "5556803288": {"available": "may 01", "content": 1408, "laundry": "laundry on site", "furnished": NaN, "price": 760, "time": "18:09:29", "dog": 0, "bed": 1, "bath": 1, "feet": NaN, "date": "2016-04-25", "long": NaN, "parking": "street parking", "lat": NaN, "smoking": "no smoking", "getphotos": 9, "cat": 0, "hasmap": 0, "wheelchair": NaN, "housingtype": "house"}, "5562346637": {"available": "apr 29", "feet": 2319, "laundry": "w/d in unit", "furnished": NaN, "price": 2100, "parking": "attached garage", "dog": 0, "bed": 3, "bath": 2, "content": 1063, "lat": 45.4983, "long": -122.6913, "time": "09:13:08", "date": "2016-04-29", "smoking": NaN, "getphotos": 8, "cat": 0, "hasmap": 1, "wheelchair": NaN, "housingtype": "house"}, "5562427073": {"available": "may 01", "content": 913, "laundry": "w/d in unit", "furnished": NaN, "price": 2150, "time": "09:56:18", "dog": 0, "bed": 3, "bath": 2, "feet": 1200, "date": "2016-04-29", "long": -122.628322, "parking": "off-street parking", "lat": 45.490143, "smoking": "no smoking", "getphotos": 5, "cat": 1, "hasmap": 1, "wheelchair": NaN, "housingtype": "apartment"}, "5562444167": {"available": "may 20", "feet": 890, "laundry": "w/d hookups", "furnished": NaN, "price": 995, "parking": "off-street parking", "dog": 0, "bed": 2, "bath": 2, "content": 1310, "lat": 45.498986, "long": -122.568347, "time": "10:05:20", "date": "2016-04-29", "smoking": NaN, "getphotos": 7, "cat": 0, "hasmap": 1, "wheelchair": NaN, "housingtype": "apartment"}, "5515341810": {"available": "mar 30", "content": 1267, "laundry": "w/d in unit", "furnished": NaN, "price": 1800, "time": "10:29:07", "dog": 0, "bed": 0, "bath": 1, "feet": 701, "date": "2016-03-30", "long": -122.69983, "parking": "off-street parking", "lat": 45.53476, "smoking": "no smoking", "getphotos": 17, "cat": 0, "hasmap": 1, "wheelchair": NaN, "housingtype": "condo"}, "5562424738": {"available": "apr 29", "feet": 694, "laundry": "w/d in unit", "furnished": NaN, "price": 1634, "parking": "attached garage", "dog": 1, "bed": 0, "bath": 1, "content": 3039, "lat": 45.534779, "long": -122.698795, "time": "09:55:03", "date": "2016-04-29", "smoking": "no smoking", "getphotos": 17, "cat": 1, "hasmap": 1, "wheelchair": "wheelchair accessible", "housingtype": "apartment"}, "5562456459": {"available": "apr 24", "content": 1997, "laundry": "laundry in bldg", "furnished": NaN, "price": 1469, "time": "10:11:54", "dog": 1, "bed": 2, "bath": 1, "feet": 725, "date": "2016-04-29", "long": -122.684778, "parking": "attached garage", "lat": 45.512971, "smoking": "no smoking", "getphotos": 12, "cat": 1, "hasmap": 1, "wheelchair": "wheelchair accessible", "housingtype": "apartment"}, "5562454304": {"available": "apr 29", "content": 2541, "laundry": "w/d in unit", "furnished": NaN, "price": 2880, "time": "10:10:43", "dog": 1, "bed": 2, "bath": 2, "feet": 966, "date": "2016-04-29", "long": -122.6854, "parking": "attached garage", "lat": 45.527, "smoking": "no smoking", "getphotos": 13, "cat": 1, "hasmap": 1, "wheelchair": "wheelchair accessible", "housingtype": "apartment"}, "5562430632": {"available": "may 01", "content": 1734, "laundry": "w/d in unit", "furnished": NaN, "price": 1584, "time": "09:58:10", "dog": 1, "bed": 0, "bath": 1, "feet": 538, "date": "2016-04-29", "long": -122.680334, "parking": "attached garage", "lat": 45.511558, "smoking": "no smoking", "getphotos": 14, "cat": 1, "hasmap": 1, "wheelchair": "wheelchair accessible", "housingtype": "apartment"}, "5562460134": {"available": "jun 01", "content": 2362, "laundry": "w/d in unit", "furnished": NaN, "price": 2395, "time": "10:13:50", "dog": 0, "bed": 4, "bath": "2.5", "feet": 1821, "date": "2016-04-29", "long": -122.582878, "parking": "attached garage", "lat": 45.502984, "smoking": "no smoking", "getphotos": 7, "cat": 0, "hasmap": 1, "wheelchair": NaN, "housingtype": "house"}, "5562448910": {"available": "may 03", "content": 1741, "laundry": "laundry on site", "furnished": NaN, "price": 1330, "time": "10:07:49", "dog": 1, "bed": 2, "bath": 1, "feet": 902, "date": "2016-04-29", "long": -122.533607, "parking": "carport", "lat": 45.55545, "smoking": "no smoking", "getphotos": 9, "cat": 1, "hasmap": 1, "wheelchair": NaN, "housingtype": "apartment"}, "5562445314": {"available": "may 20", "feet": 890, "laundry": "w/d hookups", "furnished": NaN, "price": 995, "parking": "off-street parking", "dog": 0, "bed": 2, "bath": 2, "content": 1220, "lat": 45.498986, "long": -122.568347, "time": "10:05:55", "date": "2016-04-29", "smoking": NaN, "getphotos": 8, "cat": 0, "hasmap": 1, "wheelchair": NaN, "housingtype": "apartment"}, "5562409018": {"available": "apr 29", "feet": NaN, "laundry": NaN, "furnished": NaN, "price": 900, "parking": NaN, "dog": 0, "bed": 8, "bath": 1, "content": 949, "lat": 45.56, "long": -122.6001, "time": "09:46:43", "date": "2016-04-29", "smoking": NaN, "getphotos": 0, "cat": 0, "hasmap": 1, "wheelchair": NaN, "housingtype": "apartment"}, "5562436458": {"available": "may 15", "content": 2070, "laundry": "w/d in unit", "furnished": NaN, "price": 2200, "time": "10:01:17", "dog": 1, "bed": 3, "bath": 2, "feet": 1320, "date": "2016-04-29", "long": -122.5596, "parking": "attached garage", "lat": 45.4762, "smoking": "no smoking", "getphotos": 24, "cat": 1, "hasmap": 1, "wheelchair": NaN, "housingtype": "townhouse"}, "5533022121": {"available": "jul 01", "content": 801, "laundry": "laundry on site", "furnished": NaN, "price": 1700, "time": "15:36:46", "dog": 0, "bed": 2, "bath": "1.5", "feet": 900, "date": "2016-04-10", "long": -122.709174, "parking": "street parking", "lat": 45.533259, "smoking": "no smoking", "getphotos": 8, "cat": 0, "hasmap": 1, "wheelchair": NaN, "housingtype": "apartment"}, "5546666598": {"available": "apr 19", "content": 1549, "laundry": "w/d in unit", "furnished": NaN, "price": 960, "time": "10:17:07", "dog": 0, "bed": 2, "bath": 1, "feet": NaN, "date": "2016-04-19", "long": -122.496426, "parking": "off-street parking", "lat": 45.524993, "smoking": NaN, "getphotos": 8, "cat": 0, "hasmap": 1, "wheelchair": NaN, "housingtype": "apartment"}, "5562473997": {"available": "apr 29", "content": 1511, "laundry": "laundry on site", "furnished": NaN, "price": 825, "time": "10:21:13", "dog": 0, "bed": 0, "bath": 1, "feet": 340, "date": "2016-04-29", "long": -122.685678, "parking": "street parking", "lat": 45.517715, "smoking": "no smoking", "getphotos": 7, "cat": 0, "hasmap": 1, "wheelchair": NaN, "housingtype": "apartment"}, "5562450516": {"available": "apr 29", "feet": 435, "laundry": "laundry on site", "furnished": NaN, "price": 1191, "parking": "attached garage", "dog": 1, "bed": 1, "bath": 1, "content": 2264, "lat": 45.512971, "long": -122.684778, "time": "10:08:41", "date": "2016-04-29", "smoking": "no smoking", "getphotos": 15, "cat": 0, "hasmap": 1, "wheelchair": "wheelchair accessible", "housingtype": "apartment"}, "5562432717": {"available": "apr 29", "content": 539, "laundry": "w/d in unit", "furnished": NaN, "price": 1602, "time": "09:59:19", "dog": 1, "bed": 3, "bath": 2, "feet": 1178, "date": "2016-04-29", "long": -122.401344, "parking": NaN, "lat": 45.516476, "smoking": NaN, "getphotos": 8, "cat": 1, "hasmap": 1, "wheelchair": NaN, "housingtype": "apartment"}, "5562475476": {"available": "apr 29", "content": 1670, "laundry": "w/d in unit", "furnished": NaN, "price": 1250, "time": "10:21:59", "dog": 1, "bed": 2, "bath": 2, "feet": 924, "date": "2016-04-29", "long": -122.467578, "parking": "carport", "lat": 45.486016, "smoking": "no smoking", "getphotos": 10, "cat": 1, "hasmap": 1, "wheelchair": NaN, "housingtype": "apartment"}, "5562432902": {"available": "may 07", "feet": 700, "laundry": "laundry on site", "furnished": NaN, "price": 1270, "parking": NaN, "dog": 1, "bed": 2, "bath": 1, "content": 2780, "lat": 45.510092, "long": -122.578671, "time": "09:59:25", "date": "2016-04-29", "smoking": NaN, "getphotos": 11, "cat": 1, "hasmap": 1, "wheelchair": NaN, "housingtype": "apartment"}}